verilog/12-03/parallel_interfaces/hs_parallel_in.v
// un'interfaccia parallela di ingresso con handshake su 8 bit
module hs_parallel_in(clock, reset_, 
											s_, ior_, a0, dav_, rfd, d7_d0, byte_in);
	input clock, reset_;

	input s_, ior_;
	input a0;
	
	input dav_;
	output rfd;
	
	output[7:0] d7_d0;
	input[7:0] byte_in;
	
	wire e_b, e_s;
	hs_parallel_in_comb comb (
		.s_(s_), .ior_(ior_), .a0(a0),
		.e_b(e_b), .e_s(e_s)
	);

	wire[7:0] rbr;
	wire fi;

	hs_parallel_in_seq seq (
		.clock(clock), .reset_(reset_),
		.dav_(dav_), .rfd(rfd), .e_b(e_b),
		.byte_in(byte_in), .fi(fi), .rbr(rbr)
	);

	assign d7_d0 = e_b ? rbr:
								 e_s ? {7'BZ, fi}:
								 /*dc*/8'BZ;	
endmodule

module hs_parallel_in_seq(clock, reset_, 
													e_b, dav_, rfd, byte_in, fi, rbr);
	input clock, reset_;
												
	input e_b;
	
	input dav_;
	output rfd;

	reg RFD;
	assign rfd = RFD;

	input[7:0] byte_in;

	output fi;

	reg FI;
	assign fi = FI;

	output[7:0] rbr;

	reg[7:0] RBR;
	assign rbr = RBR;

	reg[1:0] STAR;
	localparam
		s0 = 2'B00,
		s1 = 2'B01,
		s2 = 2'B10,
		s3 = 2'B11;

	always @(reset_) if(reset_ == 0) #1 begin
		RFD <= 1;
		FI <= 0;
		STAR <= s0;
	end

	always @(posedge clock) if(reset_ == 1) #3 begin
		casex(STAR)
			s0: begin
				RFD <= 1;
				RBR <= byte_in;
				FI <= 0;
				STAR <= (dav_ == 0) ? s1 : s0;
			end
			s1: begin
				RFD <= 0;
				STAR <= (dav_ == 1) ? s2: s1;
			end
			s2: begin
				FI <= 1;
				STAR <= (e_b == 1) ? s3 : s2;
			end
			s3: begin
				STAR <= (e_b == 0) ? s0 : s3;
			end
		endcase
	end
endmodule

module hs_parallel_in_comb(s_, ior_, a0, e_b, e_s);
	input s_, ior_, a0;
	output e_b, e_s;

	assign {e_b, e_s} = ({s_, ior_, a0} == 3'B000) ? 'B01:
									 		({s_, ior_, a0} == 3'B001) ? 'B10:
									 		/* 				don't care 			*/ 'B00;
endmodule

verilog/12-03/tests/hs_parallel_in_bench.v
module testbench();
	reg t_clock, t_reset_;
	reg t_s_, t_ior_, t_a0, t_dav_;
	reg[7:0] t_byte_in;
	wire t_rfd;
	wire[7:0] t_d7_d0;

	hs_parallel_in hs_in (
		.clock(t_clock), .reset_(t_reset_), 
		.s_(t_s_), .ior_(t_ior_), .a0(t_a0), 
		.dav_(t_dav_), .rfd(t_rfd),
		.d7_d0(t_d7_d0), .byte_in(t_byte_in)
	);

	initial forever #3 t_clock = ~t_clock;

	initial begin 
		$dumpfile("hs_parallel_in_waveform.vcd");
		$dumpvars;	

		t_s_ = 1;
		t_ior_ = 1;

		t_reset_ = 1;
		t_clock = 0;

		t_dav_ = 1;

		t_byte_in = 'H4F;

		#20;

		t_dav_ = 0;

		#20;

		t_dav_ = 1;

		#20;

		t_s_ = 0;

		t_a0 = 0;
		t_ior_ = 0;

		#20;

		t_a0 = 1;
		t_ior_ = 1;
		
		#20;

		t_ior_ = 0;

		#20;

		t_ior_ = 1;

		#20;

		$finish;
	end
endmodule

verilog/12-03/tests/hs_parallel_in_waveform.vcd
$date
	Mon Jan  6 21:50:19 2025
$end
$version
	Icarus Verilog
$end
$timescale
	1s
$end
$scope module testbench $end
$var wire 1 ! t_rfd $end
$var wire 8 " t_d7_d0 [7:0] $end
$var reg 1 # t_a0 $end
$var reg 8 $ t_byte_in [7:0] $end
$var reg 1 % t_clock $end
$var reg 1 & t_dav_ $end
$var reg 1 ' t_ior_ $end
$var reg 1 ( t_reset_ $end
$var reg 1 ) t_s_ $end
$scope module hs_in $end
$var wire 1 # a0 $end
$var wire 8 * byte_in [7:0] $end
$var wire 1 % clock $end
$var wire 1 & dav_ $end
$var wire 1 ' ior_ $end
$var wire 1 ( reset_ $end
$var wire 1 ) s_ $end
$var wire 1 ! rfd $end
$var wire 8 + rbr [7:0] $end
$var wire 1 , fi $end
$var wire 1 - e_s $end
$var wire 1 . e_b $end
$var wire 8 / d7_d0 [7:0] $end
$scope module comb $end
$var wire 1 # a0 $end
$var wire 1 ' ior_ $end
$var wire 1 ) s_ $end
$var wire 1 - e_s $end
$var wire 1 . e_b $end
$upscope $end
$scope module seq $end
$var wire 8 0 byte_in [7:0] $end
$var wire 1 % clock $end
$var wire 1 & dav_ $end
$var wire 1 . e_b $end
$var wire 1 , fi $end
$var wire 8 1 rbr [7:0] $end
$var wire 1 ( reset_ $end
$var wire 1 ! rfd $end
$var parameter 2 2 s0 $end
$var parameter 2 3 s1 $end
$var parameter 2 4 s2 $end
$var parameter 2 5 s3 $end
$var reg 1 , FI $end
$var reg 8 6 RBR [7:0] $end
$var reg 1 7 RFD $end
$var reg 2 8 STAR [1:0] $end
$upscope $end
$upscope $end
$upscope $end
$enddefinitions $end
$comment Show the parameter values. $end
$dumpall
b11 5
b10 4
b1 3
b0 2
$end
#0
$dumpvars
bx 8
x7
bx 6
bx 1
b1001111 0
bx /
0.
0-
x,
bx +
b1001111 *
1)
1(
1'
1&
0%
b1001111 $
x#
bx "
x!
$end
#3
1%
#6
b0 8
0,
b1001111 +
b1001111 1
b1001111 6
1!
17
0%
#9
1%
#12
0%
#15
1%
#18
0%
#20
0&
#21
1%
#24
b1 8
0%
#27
1%
#30
0!
07
0%
#33
1%
#36
0%
#39
1%
#40
1&
#42
b10 8
0%
#45
1%
#48
1,
0%
#51
1%
#54
0%
#57
1%
#60
b1 "
b1 /
1-
0%
0'
0#
0)
#63
1%
#66
0%
#69
1%
#72
0%
#75
1%
#78
0%
#80
bx "
bx /
0-
1'
1#
#81
1%
#84
0%
#87
1%
#90
0%
#93
1%
#96
0%
#99
1%
#100
b1001111 "
b1001111 /
1.
0'
#102
b11 8
0%
#105
1%
#108
0%
#111
1%
#114
0%
#117
1%
#120
bx "
bx /
0.
0%
1'
#123
1%
#126
b0 8
0%
#129
1%
#132
0,
1!
17
0%
