verilog/12-03/parallel_interfaces/hs_parallel_out.v
// un'interfaccia parallela di ingresso con handshake su 8 bit
module hs_parallel_out(clock, reset_,
										 s_, ior_, iow_, a0, dav_, rfd, d7_d0, byte_out);
	input clock, reset_;

	input s_, ior_, iow_;
	input a0;
	
	output dav_;
	input rfd;
	
	inout[7:0] d7_d0;
	output[7:0] byte_out;
	
	wire e_b, e_s;
	hs_parallel_out_comb comb (
		.s_(s_), .ior_(ior_), .iow_(iow_), .a0(a0),
		.e_b(e_b), .e_s(e_s)
	);

	wire fo;

	hs_parallel_out_seq seq (
		.clock(clock), .reset_(reset_),
		.dav_(dav_), .rfd(rfd), .e_b(e_b),
		.byte_out(byte_out), .fo(fo), .d7_d0(d7_d0)
	);

	assign d7_d0 = e_s ? {3'BZ, fo, 4'BZ}:
								 /*dc*/8'BZ;	
endmodule

module hs_parallel_out_seq(clock, reset_, 
													 e_b, dav_, rfd, byte_out, fo, d7_d0);
	input clock, reset_;
												
	input e_b;
	
	output dav_;
	input rfd;

	reg DAV;
	assign dav_ = DAV;

	output[7:0] byte_out;
	
	input[7:0] d7_d0;

	output fo;

	reg FO;
	assign fo = FO;

	reg[7:0] TBR;
	assign byte_out = TBR;

	reg[1:0] STAR;
	localparam
		s0 = 2'B00,
		s1 = 2'B01,
		s2 = 2'B10,
		s3 = 2'B11;

	always @(reset_) if(reset_ == 0) #1 begin
		DAV <= 1;
		FO <= 1;
		STAR <= s0;
	end

	always @(posedge clock) if(reset_ == 1) #3 begin
		casex(STAR)
			s0: begin
				TBR <= d7_d0;
				FO <= 1;
				STAR <= (e_b == 1) ? s1 : s0;
			end
			s1: begin
				FO <= 0;
				STAR <= (e_b == 0) ? s2 : s1;
			end
			s2: begin
				DAV <= 0;
				STAR <= (rfd == 0) ? s3 : s2;
			end
			s3: begin
				DAV <= 1;
				STAR <= (rfd == 1) ? s0 : s3;
			end
		endcase
	end
endmodule

module hs_parallel_out_comb(s_, ior_, iow_, a0, e_b, e_s);
	input s_, ior_, iow_, a0;
	output e_b, e_s;

	assign {e_b, e_s} = ({s_, ior_, iow_, a0} == 4'B0010) ? 'B01:
									 		({s_, ior_, iow_, a0} == 4'B0101) ? 'B10:
									 		/* 				    don't care 				 */ 'B00;
endmodule

verilog/12-03/tests/hs_parallel_out_bench.v
module testbench();
	reg t_clock, t_reset_;
	reg t_s_, t_ior_, t_iow_, t_a0, t_rfd;
	wire[7:0] t_byte_out;
	wire t_dav_;
	
	wire[7:0] t_d7_d0;
	reg[7:0] t_d7_d0_driver;
	assign t_d7_d0 = t_d7_d0_driver;

	hs_parallel_out hs_out (
		.clock(t_clock), .reset_(t_reset_), 
		.s_(t_s_), .ior_(t_ior_), .iow_(t_iow_), .a0(t_a0), 
		.dav_(t_dav_), .rfd(t_rfd),
		.d7_d0(t_d7_d0), .byte_out(t_byte_out)
	);

	initial forever #3 t_clock = ~t_clock;

	initial begin 
		$dumpfile("hs_parallel_out_waveform.vcd");
		$dumpvars;	

		t_s_ = 1;
		t_ior_ = 1;
		t_iow_ = 1;

		t_reset_ = 1;
		t_clock = 0;

		t_rfd = 1;
		t_d7_d0_driver = 'BZ;

		#20;

		t_s_ = 0;
		
		t_a0 = 0;
		t_ior_ = 0;

		#20;

		t_a0 = 1;
		t_ior_ = 1;
		t_d7_d0_driver = 'H4F;

		#20;

		t_iow_ = 0;
		
		#20;

		t_d7_d0_driver = 'BZ;
		t_iow_ = 1;

		#20;
		
		t_a0 = 0;
		t_ior_ = 0;

		#20;

		t_a0 = 1;
		t_ior_ = 1;

		#20;

		t_rfd = 0;

		#20;

		t_rfd = 1;

		#20;

		$finish;
	end
endmodule

verilog/12-03/tests/hs_parallel_out_waveform.vcd
$date
	Mon Jan  6 22:12:04 2025
$end
$version
	Icarus Verilog
$end
$timescale
	1s
$end
$scope module testbench $end
$var wire 8 ! t_d7_d0 [7:0] $end
$var wire 1 " t_dav_ $end
$var wire 8 # t_byte_out [7:0] $end
$var reg 1 $ t_a0 $end
$var reg 1 % t_clock $end
$var reg 8 & t_d7_d0_driver [7:0] $end
$var reg 1 ' t_ior_ $end
$var reg 1 ( t_iow_ $end
$var reg 1 ) t_reset_ $end
$var reg 1 * t_rfd $end
$var reg 1 + t_s_ $end
$scope module hs_out $end
$var wire 1 $ a0 $end
$var wire 1 % clock $end
$var wire 8 , d7_d0 [7:0] $end
$var wire 1 ' ior_ $end
$var wire 1 ( iow_ $end
$var wire 1 ) reset_ $end
$var wire 1 * rfd $end
$var wire 1 + s_ $end
$var wire 1 - fo $end
$var wire 1 . e_s $end
$var wire 1 / e_b $end
$var wire 1 " dav_ $end
$var wire 8 0 byte_out [7:0] $end
$scope module comb $end
$var wire 1 $ a0 $end
$var wire 1 ' ior_ $end
$var wire 1 ( iow_ $end
$var wire 1 + s_ $end
$var wire 1 . e_s $end
$var wire 1 / e_b $end
$upscope $end
$scope module seq $end
$var wire 8 1 byte_out [7:0] $end
$var wire 1 % clock $end
$var wire 8 2 d7_d0 [7:0] $end
$var wire 1 " dav_ $end
$var wire 1 / e_b $end
$var wire 1 - fo $end
$var wire 1 ) reset_ $end
$var wire 1 * rfd $end
$var parameter 2 3 s0 $end
$var parameter 2 4 s1 $end
$var parameter 2 5 s2 $end
$var parameter 2 6 s3 $end
$var reg 1 7 DAV $end
$var reg 1 - FO $end
$var reg 2 8 STAR [1:0] $end
$var reg 8 9 TBR [7:0] $end
$upscope $end
$upscope $end
$upscope $end
$enddefinitions $end
$comment Show the parameter values. $end
$dumpall
b11 6
b10 5
b1 4
b0 3
$end
#0
$dumpvars
bx 9
bx 8
x7
bz 2
bx 1
bx 0
0/
0.
x-
bz ,
1+
1*
1)
1(
1'
bz &
0%
x$
bx #
x"
bz !
$end
#3
1%
#6
b0 8
1-
bz #
bz 0
bz 1
bz 9
0%
#9
1%
#12
0%
#15
1%
#18
0%
#20
b10000 !
b10000 ,
b10000 2
1.
0'
0$
0+
#21
1%
#24
b10000 #
b10000 0
b10000 1
b10000 9
0%
#27
1%
#30
0%
#33
1%
#36
0%
#39
1%
#40
0.
b1001111 !
b1001111 ,
b1001111 2
b1001111 &
1'
1$
#42
b1001111 #
b1001111 0
b1001111 1
b1001111 9
0%
#45
1%
#48
0%
#51
1%
#54
0%
#57
1%
#60
1/
0%
0(
#63
1%
#66
b1 8
0%
#69
1%
#72
0-
0%
#75
1%
#78
0%
#80
0/
1(
bz !
bz ,
bz 2
bz &
#81
1%
#84
b10 8
0%
#87
1%
#90
0"
07
0%
#93
1%
#96
0%
#99
1%
#100
b0 !
b0 ,
b0 2
1.
0'
0$
#102
0%
#105
1%
#108
0%
#111
1%
#114
0%
#117
1%
#120
bz !
bz ,
bz 2
0.
0%
1'
1$
#123
1%
#126
0%
#129
1%
#132
0%
#135
1%
#138
0%
#140
0*
#141
1%
#144
b11 8
0%
#147
1%
#150
1"
17
0%
#153
1%
#156
0%
#159
1%
#160
1*
#162
b0 8
0%
#165
1%
#168
1-
bz #
bz 0
bz 1
bz 9
0%
