verilog/10-22/b10_halfadder.v
// un half adder in base 10 che calcola @x3_x0 + @cin, mettendo il 
// risultato in @s3_s0 e il riporto in @cout
// module b10_halfadder(x3_x0, cin, s3_s0, cout);
// 	input[3:0] x3_x0;
// 	input cin;
// 	output[3:0] s3_s0;
// 	output cout;
// 
// 	assign {s3_s0, cout} = ({x3_x0, cin} == 'B00000) ? 'B00000:
// 										 		 ({x3_x0, cin} == 'B00001) ? 'B00010:
// 										 		 ({x3_x0, cin} == 'B00010) ? 'B00010:
// 										 		 ({x3_x0, cin} == 'B00011) ? 'B00100:
// 										 		 ({x3_x0, cin} == 'B00100) ? 'B00100:
// 										 		 ({x3_x0, cin} == 'B00101) ? 'B00110:
// 										 		 ({x3_x0, cin} == 'B00110) ? 'B00110:
// 										 		 ({x3_x0, cin} == 'B00111) ? 'B01000:
// 										 		 ({x3_x0, cin} == 'B01000) ? 'B01000:
// 										 		 ({x3_x0, cin} == 'B01001) ? 'B01010:
// 										 		 ({x3_x0, cin} == 'B01010) ? 'B01010:
// 										 		 ({x3_x0, cin} == 'B01011) ? 'B01100:
// 										 		 ({x3_x0, cin} == 'B01100) ? 'B01100:
// 										 		 ({x3_x0, cin} == 'B01101) ? 'B01110:
// 										 		 ({x3_x0, cin} == 'B01110) ? 'B01110:
// 										 		 ({x3_x0, cin} == 'B01111) ? 'B10000:
// 										 		 ({x3_x0, cin} == 'B10000) ? 'B10000:
// 										 		 ({x3_x0, cin} == 'B10001) ? 'B10010:
// 										 		 ({x3_x0, cin} == 'B10010) ? 'B10010:
// 										 		 ({x3_x0, cin} == 'B10011) ? 'B00001:
// 										 		 /* 		  don't care 		  */ 'BXXXXX;
// endmodule

// implementazione a porte logiche
module b10_halfadder(x3_x0, cin, s3_s0, cout);
	input[3:0] x3_x0;
	wire x3 = x3_x0[3];
	wire x2 = x3_x0[2];
	wire x1 = x3_x0[1];
	wire x0 = x3_x0[0];

	input cin;
	
	output[3:0] s3_s0;	
	output cout;
	
	assign s3_s0[3] = ~x3 & x2 & x1 & x0 & cin | x3 & ~x0 | x3 & ~cin;
	assign s3_s0[2] = ~x2 & x1 & x0 & cin | x2 & ~x1 | x2 & ~x0 |
										 x2 & ~cin;
	assign s3_s0[1] = ~x3 & ~x1 & x0 & cin | x1 & ~x0 | x1 & ~cin;
	assign s3_s0[0] = x0 ^ cin;
	assign cout = x3 & x0 & cin;
endmodule

verilog/11-07/b10_counter.v
// un contatore a una cifra in base 10 che prende @ei come enabler, e 
// mette la sua uscita in @q3_q0, con eventuale riporto in @eu 
module b10_counter(eu, q3_q0, ei, clock, reset_);
  input clock, reset_;
  input ei;
  output eu;
	output[3:0] q3_q0;
  
	reg[3:0] OUTR;
  assign q3_q0 = OUTR;	
  
	wire[3:0] a3_a0; // l'uscita dell'incrementatore
	b10_halfadder inc (
		.x3_x0(q3_q0), .cin(ei),
		.s3_s0(a3_a0), .cout(eu)
	);

  always @(reset_ == 0) #1 OUTR <= 0;
  always @(posedge clock) if (reset_==1) #2 OUTR <= a3_a0;
endmodule

verilog/testbenches/b10_counter_bench.v
module testbench();
	reg t_clock, t_reset_;
	reg t_ei;
	wire t_eu;
	wire[3:0] t_q3_q0;

	b10_counter count (
		.clock(t_clock), .reset_(t_reset_),
		.ei(t_ei),
		.eu(t_eu), .q3_q0(t_q3_q0)
	);
	
	initial begin
    forever #5 t_clock = ~t_clock; 
	end

	initial begin
		$dumpfile("b10_counter_bench_waveform.vcd");
		$dumpvars;	

		t_clock = 0;
		t_reset_ = 0;
		t_ei = 0;

		#10 

		t_reset_ = 1;
		t_ei = 1;

		#200;

		$finish;
	end
endmodule

verilog/testbenches/b10_counter_bench_waveform.vcd
$date
	Wed Nov 20 00:34:48 2024
$end
$version
	Icarus Verilog
$end
$timescale
	1s
$end
$scope module testbench $end
$var wire 4 ! t_q3_q0 [3:0] $end
$var wire 1 " t_eu $end
$var reg 1 # t_clock $end
$var reg 1 $ t_ei $end
$var reg 1 % t_reset_ $end
$scope module count $end
$var wire 1 # clock $end
$var wire 1 $ ei $end
$var wire 4 & q3_q0 [3:0] $end
$var wire 1 % reset_ $end
$var wire 1 " eu $end
$var wire 4 ' a3_a0 [3:0] $end
$var reg 4 ( OUTR [3:0] $end
$scope module inc $end
$var wire 1 $ cin $end
$var wire 1 " cout $end
$var wire 4 ) x3_x0 [3:0] $end
$var wire 1 * x3 $end
$var wire 1 + x2 $end
$var wire 1 , x1 $end
$var wire 1 - x0 $end
$var wire 4 . s3_s0 [3:0] $end
$upscope $end
$upscope $end
$upscope $end
$enddefinitions $end
$comment Show the parameter values. $end
$dumpall
$end
#0
$dumpvars
bx .
x-
x,
x+
x*
bx )
bx (
bx '
bx &
0%
0$
0#
0"
bx !
$end
#1
b0 '
b0 .
0*
0+
0,
0-
b0 !
b0 &
b0 (
b0 )
#5
1#
#10
b1 '
b1 .
0#
1$
1%
#15
1#
#17
b10 '
b10 .
1-
b1 !
b1 &
b1 (
b1 )
#20
0#
#25
1#
#27
b11 '
b11 .
1,
0-
b10 !
b10 &
b10 (
b10 )
#30
0#
#35
1#
#37
b100 '
b100 .
1-
b11 !
b11 &
b11 (
b11 )
#40
0#
#45
1#
#47
b101 '
b101 .
1+
0,
0-
b100 !
b100 &
b100 (
b100 )
#50
0#
#55
1#
#57
b110 '
b110 .
1-
b101 !
b101 &
b101 (
b101 )
#60
0#
#65
1#
#67
b111 '
b111 .
1,
0-
b110 !
b110 &
b110 (
b110 )
#70
0#
#75
1#
#77
b1000 '
b1000 .
1-
b111 !
b111 &
b111 (
b111 )
#80
0#
#85
1#
#87
b1001 '
b1001 .
1*
0+
0,
0-
b1000 !
b1000 &
b1000 (
b1000 )
#90
0#
#95
1#
#97
1"
b0 '
b0 .
1-
b1001 !
b1001 &
b1001 (
b1001 )
#100
0#
#105
1#
#107
0"
b1 '
b1 .
0*
0-
b0 !
b0 &
b0 (
b0 )
#110
0#
#115
1#
#117
b10 '
b10 .
1-
b1 !
b1 &
b1 (
b1 )
#120
0#
#125
1#
#127
b11 '
b11 .
1,
0-
b10 !
b10 &
b10 (
b10 )
#130
0#
#135
1#
#137
b100 '
b100 .
1-
b11 !
b11 &
b11 (
b11 )
#140
0#
#145
1#
#147
b101 '
b101 .
1+
0,
0-
b100 !
b100 &
b100 (
b100 )
#150
0#
#155
1#
#157
b110 '
b110 .
1-
b101 !
b101 &
b101 (
b101 )
#160
0#
#165
1#
#167
b111 '
b111 .
1,
0-
b110 !
b110 &
b110 (
b110 )
#170
0#
#175
1#
#177
b1000 '
b1000 .
1-
b111 !
b111 &
b111 (
b111 )
#180
0#
#185
1#
#187
b1001 '
b1001 .
1*
0+
0,
0-
b1000 !
b1000 &
b1000 (
b1000 )
#190
0#
#195
1#
#197
1"
b0 '
b0 .
1-
b1001 !
b1001 &
b1001 (
b1001 )
#200
0#
#205
1#
#207
0"
b1 '
b1 .
0*
0-
b0 !
b0 &
b0 (
b0 )
