verilog/10-22/b3_halfadder.v
// un half adder in base 3 che calcola @x1_x0 + @cin, mettendo il 
// risultato in @s1_s0 e il riporto in @cout
// module b3_halfadder(x1_x0, cin, s1_s0, cout);
// 	input[1:0] x1_x0;
// 	input cin;
// 	output[1:0] s1_s0;
// 	output cout;
// 
// 	assign {s1_s0, cout} = ({x1_x0, cin} == 'B000) ? 'B000:
// 										 		 ({x1_x0, cin} == 'B001) ? 'B010:
// 										 		 ({x1_x0, cin} == 'B010) ? 'B010:
// 										 		 ({x1_x0, cin} == 'B011) ? 'B100:
// 										 		 ({x1_x0, cin} == 'B100) ? 'B100:
// 										 		 ({x1_x0, cin} == 'B101) ? 'B001:
// 										 		 /* 		 don't care 		*/ 'BXXX;
// endmodule

// implementazione a porte logiche
module b3_halfadder(x1_x0, cin, s1_s0, cout);
	input[1:0] x1_x0;
	wire x1 = x1_x0[1];
	wire x0 = x1_x0[0];

	input cin;
	
	output[1:0] s1_s0;	
	output cout;

	assign s1_s0[1] = (x1 & ~cin) | (x0 & cin);
	assign s1_s0[0] = (x0 & ~cin) | ~x1 & ~x0 & cin;
	assign cout = x1 & cin;
endmodule

verilog/11-07/b3_counter.v
// un contatore a una cifra in base 3 che prende @ei come enabler, e 
// mette la sua uscita in @q1_q0, con eventuale riporto in @eu 
module b3_counter(eu, q1_q0, ei, clock, reset_);
  input clock, reset_;
  input ei;
  output eu;
	output[1:0] q1_q0;
  
	reg[1:0] OUTR;
  assign q1_q0 = OUTR;	
  
	wire[1:0] a1_a0; // l'uscita dell'incrementatore
	b3_halfadder inc (
		.x1_x0(q1_q0), .cin(ei),
		.s1_s0(a1_a0), .cout(eu)
	);

  always @(reset_ == 0) #1 OUTR <= 0;
  always @(posedge clock) if (reset_==1) #2 OUTR <= a1_a0;
endmodule

verilog/11-07/n4_b3_counter.v
// un contatore a 4 cifre in base 3 che prende @ei come enabler, e 
// mette la sua uscita in @q31_q30, @q21_q20, @q11_q10 e @q01_q00, 
// con eventuale riporto in @eu 
module n4_b3_counter(eu, q31_q30, q21_q20, q11_q10, q01_q00, m_ei, 
																									m_clock, m_reset_);
  input m_clock, m_reset_;
  input m_ei;

	wire[3:0] eu3_eu0;
  
	output eu;
	assign eu = eu3_eu0[3];

	output[1:0] q01_q00;
	output[1:0] q11_q10;
	output[1:0] q21_q20;
	output[1:0] q31_q30;
  
	b3_counter count0 (
		.clock(m_clock), .reset_(m_reset_),
		.ei(m_ei),
		.eu(eu3_eu0[0]), .q1_q0(q01_q00)
	);
	
	b3_counter count1 (
		.clock(m_clock), .reset_(m_reset_),
		.ei(eu3_eu0[0]),
		.eu(eu3_eu0[1]), .q1_q0(q11_q10)
	);

	b3_counter count2 (
		.clock(m_clock), .reset_(m_reset_),
		.ei(eu3_eu0[1]),
		.eu(eu3_eu0[2]), .q1_q0(q21_q20)
	);

	b3_counter count3 (
		.clock(m_clock), .reset_(m_reset_),
		.ei(eu3_eu0[2]),
		.eu(eu3_eu0[3]), .q1_q0(q31_q30)
	);
endmodule

verilog/testbenches/n4_b3_counter_bench.v
module testbench();
	reg t_clock, t_reset_;
	reg t_ei;
	wire t_eu;
	wire[1:0] t_q01_q00;
	wire[1:0] t_q11_q10;
	wire[1:0] t_q21_q20;
	wire[1:0] t_q31_q30;

	n4_b3_counter count (
		.m_clock(t_clock), .m_reset_(t_reset_),
		.m_ei(t_ei),
		.eu(t_eu), 
		.q01_q00(t_q01_q00),
		.q11_q10(t_q11_q10),
		.q21_q20(t_q21_q20),
		.q31_q30(t_q31_q30)
	);
	
	initial begin
    forever #5 t_clock = ~t_clock; 
	end

	initial begin
		$dumpfile("n4_b3_counter_bench_waveform.vcd");
		$dumpvars;	

		t_clock = 0;
		t_reset_ = 0;
		t_ei = 0;

		#10 

		t_reset_ = 1;
		t_ei = 1;

		#1000;

		$finish;
	end
endmodule

verilog/testbenches/n4_b3_counter_bench_waveform.vcd
$date
	Wed Nov 20 01:43:35 2024
$end
$version
	Icarus Verilog
$end
$timescale
	1s
$end
$scope module testbench $end
$var wire 2 ! t_q31_q30 [1:0] $end
$var wire 2 " t_q21_q20 [1:0] $end
$var wire 2 # t_q11_q10 [1:0] $end
$var wire 2 $ t_q01_q00 [1:0] $end
$var wire 1 % t_eu $end
$var reg 1 & t_clock $end
$var reg 1 ' t_ei $end
$var reg 1 ( t_reset_ $end
$scope module count $end
$var wire 1 & m_clock $end
$var wire 1 ' m_ei $end
$var wire 1 ( m_reset_ $end
$var wire 2 ) q31_q30 [1:0] $end
$var wire 2 * q21_q20 [1:0] $end
$var wire 2 + q11_q10 [1:0] $end
$var wire 2 , q01_q00 [1:0] $end
$var wire 4 - eu3_eu0 [3:0] $end
$var wire 1 % eu $end
$scope module count0 $end
$var wire 1 & clock $end
$var wire 1 ' ei $end
$var wire 2 . q1_q0 [1:0] $end
$var wire 1 ( reset_ $end
$var wire 1 / eu $end
$var wire 2 0 a1_a0 [1:0] $end
$var reg 2 1 OUTR [1:0] $end
$scope module inc $end
$var wire 1 ' cin $end
$var wire 1 / cout $end
$var wire 2 2 x1_x0 [1:0] $end
$var wire 1 3 x1 $end
$var wire 1 4 x0 $end
$var wire 2 5 s1_s0 [1:0] $end
$upscope $end
$upscope $end
$scope module count1 $end
$var wire 1 & clock $end
$var wire 1 6 ei $end
$var wire 2 7 q1_q0 [1:0] $end
$var wire 1 ( reset_ $end
$var wire 1 8 eu $end
$var wire 2 9 a1_a0 [1:0] $end
$var reg 2 : OUTR [1:0] $end
$scope module inc $end
$var wire 1 6 cin $end
$var wire 1 8 cout $end
$var wire 2 ; x1_x0 [1:0] $end
$var wire 1 < x1 $end
$var wire 1 = x0 $end
$var wire 2 > s1_s0 [1:0] $end
$upscope $end
$upscope $end
$scope module count2 $end
$var wire 1 & clock $end
$var wire 1 ? ei $end
$var wire 2 @ q1_q0 [1:0] $end
$var wire 1 ( reset_ $end
$var wire 1 A eu $end
$var wire 2 B a1_a0 [1:0] $end
$var reg 2 C OUTR [1:0] $end
$scope module inc $end
$var wire 1 ? cin $end
$var wire 1 A cout $end
$var wire 2 D x1_x0 [1:0] $end
$var wire 1 E x1 $end
$var wire 1 F x0 $end
$var wire 2 G s1_s0 [1:0] $end
$upscope $end
$upscope $end
$scope module count3 $end
$var wire 1 & clock $end
$var wire 1 H ei $end
$var wire 2 I q1_q0 [1:0] $end
$var wire 1 ( reset_ $end
$var wire 1 J eu $end
$var wire 2 K a1_a0 [1:0] $end
$var reg 2 L OUTR [1:0] $end
$scope module inc $end
$var wire 1 H cin $end
$var wire 1 J cout $end
$var wire 2 M x1_x0 [1:0] $end
$var wire 1 N x1 $end
$var wire 1 O x0 $end
$var wire 2 P s1_s0 [1:0] $end
$upscope $end
$upscope $end
$upscope $end
$upscope $end
$enddefinitions $end
$comment Show the parameter values. $end
$dumpall
$end
#0
$dumpvars
bx P
xO
xN
bx M
bx L
bx K
0J
bx I
0H
bx G
xF
xE
bx D
bx C
bx B
0A
bx @
0?
bx >
x=
x<
bx ;
bx :
bx 9
08
bx 7
06
bx 5
x4
x3
bx 2
bx 1
bx 0
0/
bx .
b0 -
bx ,
bx +
bx *
bx )
0(
0'
0&
0%
bx $
bx #
bx "
bx !
$end
#1
b0 0
b0 5
b0 9
b0 >
b0 B
b0 G
b0 K
b0 P
03
04
0<
0=
0E
0F
0N
0O
b0 $
b0 ,
b0 .
b0 1
b0 2
b0 #
b0 +
b0 7
b0 :
b0 ;
b0 "
b0 *
b0 @
b0 C
b0 D
b0 !
b0 )
b0 I
b0 L
b0 M
#5
1&
#10
b1 0
b1 5
0&
1'
1(
#15
1&
#17
b10 0
b10 5
14
b1 $
b1 ,
b1 .
b1 1
b1 2
#20
0&
#25
1&
#27
b1 9
b1 >
16
b0 0
b0 5
b1 -
1/
13
04
b10 $
b10 ,
b10 .
b10 1
b10 2
#30
0&
#35
1&
#37
b1 0
b1 5
b1 9
b1 >
06
b0 -
0/
1=
03
b1 #
b1 +
b1 7
b1 :
b1 ;
b0 $
b0 ,
b0 .
b0 1
b0 2
#40
0&
#45
1&
#47
b10 0
b10 5
14
b1 $
b1 ,
b1 .
b1 1
b1 2
#50
0&
#55
1&
#57
b10 9
b10 >
16
b0 0
b0 5
b1 -
1/
13
04
b10 $
b10 ,
b10 .
b10 1
b10 2
#60
0&
#65
1&
#67
b1 0
b1 5
b0 B
b0 G
06
0?
b10 9
b10 >
0/
b0 -
08
03
1<
0=
b0 $
b0 ,
b0 .
b0 1
b0 2
b10 #
b10 +
b10 7
b10 :
b10 ;
#70
0&
#75
1&
#77
b10 0
b10 5
14
b1 $
b1 ,
b1 .
b1 1
b1 2
#80
0&
#85
1&
#87
b1 B
b1 G
b0 9
b0 >
1?
18
16
b0 0
b0 5
b11 -
1/
13
04
b10 $
b10 ,
b10 .
b10 1
b10 2
#90
0&
#95
1&
#97
b1 0
b1 5
b1 B
b1 G
0?
06
08
b0 -
0/
1F
0<
03
b1 "
b1 *
b1 @
b1 C
b1 D
b0 #
b0 +
b0 7
b0 :
b0 ;
b0 $
b0 ,
b0 .
b0 1
b0 2
#100
0&
#105
1&
#107
b10 0
b10 5
14
b1 $
b1 ,
b1 .
b1 1
b1 2
#110
0&
#115
1&
#117
b1 9
b1 >
16
b0 0
b0 5
b1 -
1/
13
04
b10 $
b10 ,
b10 .
b10 1
b10 2
#120
0&
#125
1&
#127
b1 0
b1 5
06
b1 9
b1 >
b0 -
0/
03
1=
b0 $
b0 ,
b0 .
b0 1
b0 2
b1 #
b1 +
b1 7
b1 :
b1 ;
#130
0&
#135
1&
#137
b10 0
b10 5
14
b1 $
b1 ,
b1 .
b1 1
b1 2
#140
0&
#145
1&
#147
b10 9
b10 >
16
b0 0
b0 5
b1 -
1/
13
04
b10 $
b10 ,
b10 .
b10 1
b10 2
#150
0&
#155
1&
#157
b1 B
b1 G
b1 0
b1 5
0?
b10 9
b10 >
06
08
b0 -
0/
1<
0=
03
b10 #
b10 +
b10 7
b10 :
b10 ;
b0 $
b0 ,
b0 .
b0 1
b0 2
#160
0&
#165
1&
#167
b10 0
b10 5
14
b1 $
b1 ,
b1 .
b1 1
b1 2
#170
0&
#175
1&
#177
b10 B
b10 G
b0 9
b0 >
1?
18
16
b0 0
b0 5
b11 -
1/
13
04
b10 $
b10 ,
b10 .
b10 1
b10 2
#180
0&
#185
1&
#187
b1 0
b1 5
b0 K
b0 P
06
0?
0H
b10 B
b10 G
0/
08
b0 -
0A
03
0<
1E
0F
b0 $
b0 ,
b0 .
b0 1
b0 2
b0 #
b0 +
b0 7
b0 :
b0 ;
b10 "
b10 *
b10 @
b10 C
b10 D
#190
0&
#195
1&
#197
b10 0
b10 5
14
b1 $
b1 ,
b1 .
b1 1
b1 2
#200
0&
#205
1&
#207
b1 9
b1 >
16
b0 0
b0 5
b1 -
1/
13
04
b10 $
b10 ,
b10 .
b10 1
b10 2
#210
0&
#215
1&
#217
b1 0
b1 5
b1 9
b1 >
06
b0 -
0/
1=
03
b1 #
b1 +
b1 7
b1 :
b1 ;
b0 $
b0 ,
b0 .
b0 1
b0 2
#220
0&
#225
1&
#227
b10 0
b10 5
14
b1 $
b1 ,
b1 .
b1 1
b1 2
#230
0&
#235
1&
#237
b10 9
b10 >
16
b0 0
b0 5
b1 -
1/
13
04
b10 $
b10 ,
b10 .
b10 1
b10 2
#240
0&
#245
1&
#247
b0 K
b0 P
b10 B
b10 G
b1 0
b1 5
0H
0A
06
0?
b10 9
b10 >
0/
b0 -
08
03
1<
0=
b0 $
b0 ,
b0 .
b0 1
b0 2
b10 #
b10 +
b10 7
b10 :
b10 ;
#250
0&
#255
1&
#257
b10 0
b10 5
14
b1 $
b1 ,
b1 .
b1 1
b1 2
#260
0&
#265
1&
#267
b1 K
b1 P
b0 B
b0 G
1H
b0 9
b0 >
1A
1?
18
16
b0 0
b0 5
b111 -
1/
13
04
b10 $
b10 ,
b10 .
b10 1
b10 2
#270
0&
#275
1&
#277
b1 0
b1 5
b1 K
b1 P
0H
0?
06
0A
08
b0 -
0/
1O
0E
0<
03
b1 !
b1 )
b1 I
b1 L
b1 M
b0 "
b0 *
b0 @
b0 C
b0 D
b0 #
b0 +
b0 7
b0 :
b0 ;
b0 $
b0 ,
b0 .
b0 1
b0 2
#280
0&
#285
1&
#287
b10 0
b10 5
14
b1 $
b1 ,
b1 .
b1 1
b1 2
#290
0&
#295
1&
#297
b1 9
b1 >
16
b0 0
b0 5
b1 -
1/
13
04
b10 $
b10 ,
b10 .
b10 1
b10 2
#300
0&
#305
1&
#307
b1 0
b1 5
06
b1 9
b1 >
b0 -
0/
03
1=
b0 $
b0 ,
b0 .
b0 1
b0 2
b1 #
b1 +
b1 7
b1 :
b1 ;
#310
0&
#315
1&
#317
b10 0
b10 5
14
b1 $
b1 ,
b1 .
b1 1
b1 2
#320
0&
#325
1&
#327
b10 9
b10 >
16
b0 0
b0 5
b1 -
1/
13
04
b10 $
b10 ,
b10 .
b10 1
b10 2
#330
0&
#335
1&
#337
b0 B
b0 G
b1 0
b1 5
0?
b10 9
b10 >
06
08
b0 -
0/
1<
0=
03
b10 #
b10 +
b10 7
b10 :
b10 ;
b0 $
b0 ,
b0 .
b0 1
b0 2
#340
0&
#345
1&
#347
b10 0
b10 5
14
b1 $
b1 ,
b1 .
b1 1
b1 2
#350
0&
#355
1&
#357
b1 B
b1 G
b0 9
b0 >
1?
18
16
b0 0
b0 5
b11 -
1/
13
04
b10 $
b10 ,
b10 .
b10 1
b10 2
#360
0&
#365
1&
#367
b1 0
b1 5
06
0?
b1 B
b1 G
0/
b0 -
08
03
0<
1F
b0 $
b0 ,
b0 .
b0 1
b0 2
b0 #
b0 +
b0 7
b0 :
b0 ;
b1 "
b1 *
b1 @
b1 C
b1 D
#370
0&
#375
1&
#377
b10 0
b10 5
14
b1 $
b1 ,
b1 .
b1 1
b1 2
#380
0&
#385
1&
#387
b1 9
b1 >
16
b0 0
b0 5
b1 -
1/
13
04
b10 $
b10 ,
b10 .
b10 1
b10 2
#390
0&
#395
1&
#397
b1 0
b1 5
b1 9
b1 >
06
b0 -
0/
1=
03
b1 #
b1 +
b1 7
b1 :
b1 ;
b0 $
b0 ,
b0 .
b0 1
b0 2
#400
0&
#405
1&
#407
b10 0
b10 5
14
b1 $
b1 ,
b1 .
b1 1
b1 2
#410
0&
#415
1&
#417
b10 9
b10 >
16
b0 0
b0 5
b1 -
1/
13
04
b10 $
b10 ,
b10 .
b10 1
b10 2
#420
0&
#425
1&
#427
b1 0
b1 5
b1 B
b1 G
06
0?
b10 9
b10 >
0/
b0 -
08
03
1<
0=
b0 $
b0 ,
b0 .
b0 1
b0 2
b10 #
b10 +
b10 7
b10 :
b10 ;
#430
0&
#435
1&
#437
b10 0
b10 5
14
b1 $
b1 ,
b1 .
b1 1
b1 2
#440
0&
#445
1&
#447
b10 B
b10 G
b0 9
b0 >
1?
18
16
b0 0
b0 5
b11 -
1/
13
04
b10 $
b10 ,
b10 .
b10 1
b10 2
#450
0&
#455
1&
#457
b1 K
b1 P
b1 0
b1 5
0H
b10 B
b10 G
0?
06
0A
08
b0 -
0/
1E
0F
0<
03
b10 "
b10 *
b10 @
b10 C
b10 D
b0 #
b0 +
b0 7
b0 :
b0 ;
b0 $
b0 ,
b0 .
b0 1
b0 2
#460
0&
#465
1&
#467
b10 0
b10 5
14
b1 $
b1 ,
b1 .
b1 1
b1 2
#470
0&
#475
1&
#477
b1 9
b1 >
16
b0 0
b0 5
b1 -
1/
13
04
b10 $
b10 ,
b10 .
b10 1
b10 2
#480
0&
#485
1&
#487
b1 0
b1 5
06
b1 9
b1 >
b0 -
0/
03
1=
b0 $
b0 ,
b0 .
b0 1
b0 2
b1 #
b1 +
b1 7
b1 :
b1 ;
#490
0&
#495
1&
#497
b10 0
b10 5
14
b1 $
b1 ,
b1 .
b1 1
b1 2
#500
0&
#505
1&
#507
b10 9
b10 >
16
b0 0
b0 5
b1 -
1/
13
04
b10 $
b10 ,
b10 .
b10 1
b10 2
#510
0&
#515
1&
#517
b1 K
b1 P
b10 B
b10 G
0H
b1 0
b1 5
0A
0?
b10 9
b10 >
06
08
b0 -
0/
1<
0=
03
b10 #
b10 +
b10 7
b10 :
b10 ;
b0 $
b0 ,
b0 .
b0 1
b0 2
#520
0&
#525
1&
#527
b10 0
b10 5
14
b1 $
b1 ,
b1 .
b1 1
b1 2
#530
0&
#535
1&
#537
b10 K
b10 P
b0 B
b0 G
1H
b0 9
b0 >
1A
1?
18
16
b0 0
b0 5
b111 -
1/
13
04
b10 $
b10 ,
b10 .
b10 1
b10 2
#540
0&
#545
1&
#547
b1 0
b1 5
06
0?
0H
0%
b10 K
b10 P
0/
08
0A
b0 -
0J
03
0<
0E
1N
0O
b0 $
b0 ,
b0 .
b0 1
b0 2
b0 #
b0 +
b0 7
b0 :
b0 ;
b0 "
b0 *
b0 @
b0 C
b0 D
b10 !
b10 )
b10 I
b10 L
b10 M
#550
0&
#555
1&
#557
b10 0
b10 5
14
b1 $
b1 ,
b1 .
b1 1
b1 2
#560
0&
#565
1&
#567
b1 9
b1 >
16
b0 0
b0 5
b1 -
1/
13
04
b10 $
b10 ,
b10 .
b10 1
b10 2
#570
0&
#575
1&
#577
b1 0
b1 5
b1 9
b1 >
06
b0 -
0/
1=
03
b1 #
b1 +
b1 7
b1 :
b1 ;
b0 $
b0 ,
b0 .
b0 1
b0 2
#580
0&
#585
1&
#587
b10 0
b10 5
14
b1 $
b1 ,
b1 .
b1 1
b1 2
#590
0&
#595
1&
#597
b10 9
b10 >
16
b0 0
b0 5
b1 -
1/
13
04
b10 $
b10 ,
b10 .
b10 1
b10 2
#600
0&
#605
1&
#607
b1 0
b1 5
b0 B
b0 G
06
0?
b10 9
b10 >
0/
b0 -
08
03
1<
0=
b0 $
b0 ,
b0 .
b0 1
b0 2
b10 #
b10 +
b10 7
b10 :
b10 ;
#610
0&
#615
1&
#617
b10 0
b10 5
14
b1 $
b1 ,
b1 .
b1 1
b1 2
#620
0&
#625
1&
#627
b1 B
b1 G
b0 9
b0 >
1?
18
16
b0 0
b0 5
b11 -
1/
13
04
b10 $
b10 ,
b10 .
b10 1
b10 2
#630
0&
#635
1&
#637
b1 0
b1 5
b1 B
b1 G
0?
06
08
b0 -
0/
1F
0<
03
b1 "
b1 *
b1 @
b1 C
b1 D
b0 #
b0 +
b0 7
b0 :
b0 ;
b0 $
b0 ,
b0 .
b0 1
b0 2
#640
0&
#645
1&
#647
b10 0
b10 5
14
b1 $
b1 ,
b1 .
b1 1
b1 2
#650
0&
#655
1&
#657
b1 9
b1 >
16
b0 0
b0 5
b1 -
1/
13
04
b10 $
b10 ,
b10 .
b10 1
b10 2
#660
0&
#665
1&
#667
b1 0
b1 5
06
b1 9
b1 >
b0 -
0/
03
1=
b0 $
b0 ,
b0 .
b0 1
b0 2
b1 #
b1 +
b1 7
b1 :
b1 ;
#670
0&
#675
1&
#677
b10 0
b10 5
14
b1 $
b1 ,
b1 .
b1 1
b1 2
#680
0&
#685
1&
#687
b10 9
b10 >
16
b0 0
b0 5
b1 -
1/
13
04
b10 $
b10 ,
b10 .
b10 1
b10 2
#690
0&
#695
1&
#697
b1 B
b1 G
b1 0
b1 5
0?
b10 9
b10 >
06
08
b0 -
0/
1<
0=
03
b10 #
b10 +
b10 7
b10 :
b10 ;
b0 $
b0 ,
b0 .
b0 1
b0 2
#700
0&
#705
1&
#707
b10 0
b10 5
14
b1 $
b1 ,
b1 .
b1 1
b1 2
#710
0&
#715
1&
#717
b10 B
b10 G
b0 9
b0 >
1?
18
16
b0 0
b0 5
b11 -
1/
13
04
b10 $
b10 ,
b10 .
b10 1
b10 2
#720
0&
#725
1&
#727
b10 K
b10 P
b1 0
b1 5
0%
0J
06
0?
0H
b10 B
b10 G
0/
08
b0 -
0A
03
0<
1E
0F
b0 $
b0 ,
b0 .
b0 1
b0 2
b0 #
b0 +
b0 7
b0 :
b0 ;
b10 "
b10 *
b10 @
b10 C
b10 D
#730
0&
#735
1&
#737
b10 0
b10 5
14
b1 $
b1 ,
b1 .
b1 1
b1 2
#740
0&
#745
1&
#747
b1 9
b1 >
16
b0 0
b0 5
b1 -
1/
13
04
b10 $
b10 ,
b10 .
b10 1
b10 2
#750
0&
#755
1&
#757
b1 0
b1 5
b1 9
b1 >
06
b0 -
0/
1=
03
b1 #
b1 +
b1 7
b1 :
b1 ;
b0 $
b0 ,
b0 .
b0 1
b0 2
#760
0&
#765
1&
#767
b10 0
b10 5
14
b1 $
b1 ,
b1 .
b1 1
b1 2
#770
0&
#775
1&
#777
b10 9
b10 >
16
b0 0
b0 5
b1 -
1/
13
04
b10 $
b10 ,
b10 .
b10 1
b10 2
#780
0&
#785
1&
#787
b10 K
b10 P
0%
b10 B
b10 G
0J
b1 0
b1 5
0H
0A
06
0?
b10 9
b10 >
0/
b0 -
08
03
1<
0=
b0 $
b0 ,
b0 .
b0 1
b0 2
b10 #
b10 +
b10 7
b10 :
b10 ;
#790
0&
#795
1&
#797
b10 0
b10 5
14
b1 $
b1 ,
b1 .
b1 1
b1 2
#800
0&
#805
1&
#807
b0 K
b0 P
1%
b0 B
b0 G
1J
1H
b0 9
b0 >
1A
1?
18
16
b0 0
b0 5
b1111 -
1/
13
04
b10 $
b10 ,
b10 .
b10 1
b10 2
#810
0&
#815
1&
#817
b1 0
b1 5
0%
0H
0?
06
0J
0A
08
b0 -
0/
0N
0E
0<
03
b0 !
b0 )
b0 I
b0 L
b0 M
b0 "
b0 *
b0 @
b0 C
b0 D
b0 #
b0 +
b0 7
b0 :
b0 ;
b0 $
b0 ,
b0 .
b0 1
b0 2
#820
0&
#825
1&
#827
b10 0
b10 5
14
b1 $
b1 ,
b1 .
b1 1
b1 2
#830
0&
#835
1&
#837
b1 9
b1 >
16
b0 0
b0 5
b1 -
1/
13
04
b10 $
b10 ,
b10 .
b10 1
b10 2
#840
0&
#845
1&
#847
b1 0
b1 5
06
b1 9
b1 >
b0 -
0/
03
1=
b0 $
b0 ,
b0 .
b0 1
b0 2
b1 #
b1 +
b1 7
b1 :
b1 ;
#850
0&
#855
1&
#857
b10 0
b10 5
14
b1 $
b1 ,
b1 .
b1 1
b1 2
#860
0&
#865
1&
#867
b10 9
b10 >
16
b0 0
b0 5
b1 -
1/
13
04
b10 $
b10 ,
b10 .
b10 1
b10 2
#870
0&
#875
1&
#877
b0 B
b0 G
b1 0
b1 5
0?
b10 9
b10 >
06
08
b0 -
0/
1<
0=
03
b10 #
b10 +
b10 7
b10 :
b10 ;
b0 $
b0 ,
b0 .
b0 1
b0 2
#880
0&
#885
1&
#887
b10 0
b10 5
14
b1 $
b1 ,
b1 .
b1 1
b1 2
#890
0&
#895
1&
#897
b1 B
b1 G
b0 9
b0 >
1?
18
16
b0 0
b0 5
b11 -
1/
13
04
b10 $
b10 ,
b10 .
b10 1
b10 2
#900
0&
#905
1&
#907
b1 0
b1 5
06
0?
b1 B
b1 G
0/
b0 -
08
03
0<
1F
b0 $
b0 ,
b0 .
b0 1
b0 2
b0 #
b0 +
b0 7
b0 :
b0 ;
b1 "
b1 *
b1 @
b1 C
b1 D
#910
0&
#915
1&
#917
b10 0
b10 5
14
b1 $
b1 ,
b1 .
b1 1
b1 2
#920
0&
#925
1&
#927
b1 9
b1 >
16
b0 0
b0 5
b1 -
1/
13
04
b10 $
b10 ,
b10 .
b10 1
b10 2
#930
0&
#935
1&
#937
b1 0
b1 5
b1 9
b1 >
06
b0 -
0/
1=
03
b1 #
b1 +
b1 7
b1 :
b1 ;
b0 $
b0 ,
b0 .
b0 1
b0 2
#940
0&
#945
1&
#947
b10 0
b10 5
14
b1 $
b1 ,
b1 .
b1 1
b1 2
#950
0&
#955
1&
#957
b10 9
b10 >
16
b0 0
b0 5
b1 -
1/
13
04
b10 $
b10 ,
b10 .
b10 1
b10 2
#960
0&
#965
1&
#967
b1 0
b1 5
b1 B
b1 G
06
0?
b10 9
b10 >
0/
b0 -
08
03
1<
0=
b0 $
b0 ,
b0 .
b0 1
b0 2
b10 #
b10 +
b10 7
b10 :
b10 ;
#970
0&
#975
1&
#977
b10 0
b10 5
14
b1 $
b1 ,
b1 .
b1 1
b1 2
#980
0&
#985
1&
#987
b10 B
b10 G
b0 9
b0 >
1?
18
16
b0 0
b0 5
b11 -
1/
13
04
b10 $
b10 ,
b10 .
b10 1
b10 2
#990
0&
#995
1&
#997
b0 K
b0 P
b1 0
b1 5
0H
b10 B
b10 G
0?
06
0A
08
b0 -
0/
1E
0F
0<
03
b10 "
b10 *
b10 @
b10 C
b10 D
b0 #
b0 +
b0 7
b0 :
b0 ;
b0 $
b0 ,
b0 .
b0 1
b0 2
#1000
0&
#1005
1&
#1007
b10 0
b10 5
14
b1 $
b1 ,
b1 .
b1 1
b1 2
