verilog/10-22/b10_halfadder.v
// un half adder in base 10 che calcola @x3_x0 + @cin, mettendo il 
// risultato in @s3_s0 e il riporto in @cout
// module b10_halfadder(x3_x0, cin, s3_s0, cout);
// 	input[3:0] x3_x0;
// 	input cin;
// 	output[3:0] s3_s0;
// 	output cout;
// 
// 	assign {s3_s0, cout} = ({x3_x0, cin} == 'B00000) ? 'B00000:
// 										 		 ({x3_x0, cin} == 'B00001) ? 'B00010:
// 										 		 ({x3_x0, cin} == 'B00010) ? 'B00010:
// 										 		 ({x3_x0, cin} == 'B00011) ? 'B00100:
// 										 		 ({x3_x0, cin} == 'B00100) ? 'B00100:
// 										 		 ({x3_x0, cin} == 'B00101) ? 'B00110:
// 										 		 ({x3_x0, cin} == 'B00110) ? 'B00110:
// 										 		 ({x3_x0, cin} == 'B00111) ? 'B01000:
// 										 		 ({x3_x0, cin} == 'B01000) ? 'B01000:
// 										 		 ({x3_x0, cin} == 'B01001) ? 'B01010:
// 										 		 ({x3_x0, cin} == 'B01010) ? 'B01010:
// 										 		 ({x3_x0, cin} == 'B01011) ? 'B01100:
// 										 		 ({x3_x0, cin} == 'B01100) ? 'B01100:
// 										 		 ({x3_x0, cin} == 'B01101) ? 'B01110:
// 										 		 ({x3_x0, cin} == 'B01110) ? 'B01110:
// 										 		 ({x3_x0, cin} == 'B01111) ? 'B10000:
// 										 		 ({x3_x0, cin} == 'B10000) ? 'B10000:
// 										 		 ({x3_x0, cin} == 'B10001) ? 'B10010:
// 										 		 ({x3_x0, cin} == 'B10010) ? 'B10010:
// 										 		 ({x3_x0, cin} == 'B10011) ? 'B00001:
// 										 		 /* 		  don't care 		  */ 'BXXXXX;
// endmodule

// implementazione a porte logiche
module b10_halfadder(x3_x0, cin, s3_s0, cout);
	input[3:0] x3_x0;
	wire x3 = x3_x0[3];
	wire x2 = x3_x0[2];
	wire x1 = x3_x0[1];
	wire x0 = x3_x0[0];

	input cin;
	
	output[3:0] s3_s0;	
	output cout;
	
	assign s3_s0[3] = ~x3 & x2 & x1 & x0 & cin | x3 & ~x0 | x3 & ~cin;
	assign s3_s0[2] = ~x2 & x1 & x0 & cin | x2 & ~x1 | x2 & ~x0 |
										 x2 & ~cin;
	assign s3_s0[1] = ~x3 & ~x1 & x0 & cin | x1 & ~x0 | x1 & ~cin;
	assign s3_s0[0] = x0 ^ cin;
	assign cout = x3 & x0 & cin;
endmodule

verilog/11-07/b10_counter.v
// un contatore a una cifra in base 10 che prende @ei come enabler, e 
// mette la sua uscita in @q3_q0, con eventuale riporto in @eu 
module b10_counter(eu, q3_q0, ei, clock, reset_);
  input clock, reset_;
  input ei;
  output eu;
	output[3:0] q3_q0;
  
	reg[3:0] OUTR;
  assign q3_q0 = OUTR;	
  
	wire[3:0] a3_a0; // l'uscita dell'incrementatore
	b10_halfadder inc (
		.x3_x0(q3_q0), .cin(ei),
		.s3_s0(a3_a0), .cout(eu)
	);

  always @(reset_ == 0) #1 OUTR <= 0;
  always @(posedge clock) if (reset_==1) #2 OUTR <= a3_a0;
endmodule

verilog/11-07/n4_b10_counter.v
// un contatore a 4 cifre in base 10 che prende @ei come enabler, e 
// mette la sua uscita in @q33_q30, @q23_q20, @q13_q10 e @q03_q00, 
// con eventuale riporto in @eu 
module n4_b10_counter(eu, q33_q30, q23_q20, q13_q10, q03_q00, m_ei, 
																									m_clock, m_reset_);
  input m_clock, m_reset_;
  input m_ei;

	wire[3:0] eu3_eu0;
  
	output eu;
	assign eu = eu3_eu0[3];

	output[3:0] q03_q00;
	output[3:0] q13_q10;
	output[3:0] q23_q20;
	output[3:0] q33_q30;
  
	b10_counter count0 (
		.clock(m_clock), .reset_(m_reset_),
		.ei(m_ei),
		.eu(eu3_eu0[0]), .q3_q0(q03_q00)
	);
	
	b10_counter count1 (
		.clock(m_clock), .reset_(m_reset_),
		.ei(eu3_eu0[0]),
		.eu(eu3_eu0[1]), .q3_q0(q13_q10)
	);

	b10_counter count2 (
		.clock(m_clock), .reset_(m_reset_),
		.ei(eu3_eu0[1]),
		.eu(eu3_eu0[2]), .q3_q0(q23_q20)
	);

	b10_counter count3 (
		.clock(m_clock), .reset_(m_reset_),
		.ei(eu3_eu0[2]),
		.eu(eu3_eu0[3]), .q3_q0(q33_q30)
	);
endmodule

verilog/testbenches/n4_b10_counter_bench.v
module testbench();
	reg t_clock, t_reset_;
	reg t_ei;
	wire t_eu;
	wire[3:0] t_q03_q00;
	wire[3:0] t_q13_q10;
	wire[3:0] t_q23_q20;
	wire[3:0] t_q33_q30;

	n4_b10_counter count (
		.m_clock(t_clock), .m_reset_(t_reset_),
		.m_ei(t_ei),
		.eu(t_eu), 
		.q03_q00(t_q03_q00),
		.q13_q10(t_q13_q10),
		.q23_q20(t_q23_q20),
		.q33_q30(t_q33_q30)
	);
	
	initial begin
    forever #5 t_clock = ~t_clock; 
	end

	initial begin
		$dumpfile("n4_b10_counter_bench_waveform.vcd");
		$dumpvars;	

		t_clock = 0;
		t_reset_ = 0;
		t_ei = 0;

		#10 

		t_reset_ = 1;
		t_ei = 1;

		#150000;

		$finish;
	end
endmodule

verilog/testbenches/n4_b10_counter_bench_waveform.vcd
$date
	Wed Nov 20 01:45:06 2024
$end
$version
	Icarus Verilog
$end
$timescale
	1s
$end
$scope module testbench $end
$var wire 4 ! t_q33_q30 [3:0] $end
$var wire 4 " t_q23_q20 [3:0] $end
$var wire 4 # t_q13_q10 [3:0] $end
$var wire 4 $ t_q03_q00 [3:0] $end
$var wire 1 % t_eu $end
$var reg 1 & t_clock $end
$var reg 1 ' t_ei $end
$var reg 1 ( t_reset_ $end
$scope module count $end
$var wire 1 & m_clock $end
$var wire 1 ' m_ei $end
$var wire 1 ( m_reset_ $end
$var wire 4 ) q33_q30 [3:0] $end
$var wire 4 * q23_q20 [3:0] $end
$var wire 4 + q13_q10 [3:0] $end
$var wire 4 , q03_q00 [3:0] $end
$var wire 4 - eu3_eu0 [3:0] $end
$var wire 1 % eu $end
$scope module count0 $end
$var wire 1 & clock $end
$var wire 1 ' ei $end
$var wire 4 . q3_q0 [3:0] $end
$var wire 1 ( reset_ $end
$var wire 1 / eu $end
$var wire 4 0 a3_a0 [3:0] $end
$var reg 4 1 OUTR [3:0] $end
$scope module inc $end
$var wire 1 ' cin $end
$var wire 1 / cout $end
$var wire 4 2 x3_x0 [3:0] $end
$var wire 1 3 x3 $end
$var wire 1 4 x2 $end
$var wire 1 5 x1 $end
$var wire 1 6 x0 $end
$var wire 4 7 s3_s0 [3:0] $end
$upscope $end
$upscope $end
$scope module count1 $end
$var wire 1 & clock $end
$var wire 1 8 ei $end
$var wire 4 9 q3_q0 [3:0] $end
$var wire 1 ( reset_ $end
$var wire 1 : eu $end
$var wire 4 ; a3_a0 [3:0] $end
$var reg 4 < OUTR [3:0] $end
$scope module inc $end
$var wire 1 8 cin $end
$var wire 1 : cout $end
$var wire 4 = x3_x0 [3:0] $end
$var wire 1 > x3 $end
$var wire 1 ? x2 $end
$var wire 1 @ x1 $end
$var wire 1 A x0 $end
$var wire 4 B s3_s0 [3:0] $end
$upscope $end
$upscope $end
$scope module count2 $end
$var wire 1 & clock $end
$var wire 1 C ei $end
$var wire 4 D q3_q0 [3:0] $end
$var wire 1 ( reset_ $end
$var wire 1 E eu $end
$var wire 4 F a3_a0 [3:0] $end
$var reg 4 G OUTR [3:0] $end
$scope module inc $end
$var wire 1 C cin $end
$var wire 1 E cout $end
$var wire 4 H x3_x0 [3:0] $end
$var wire 1 I x3 $end
$var wire 1 J x2 $end
$var wire 1 K x1 $end
$var wire 1 L x0 $end
$var wire 4 M s3_s0 [3:0] $end
$upscope $end
$upscope $end
$scope module count3 $end
$var wire 1 & clock $end
$var wire 1 N ei $end
$var wire 4 O q3_q0 [3:0] $end
$var wire 1 ( reset_ $end
$var wire 1 P eu $end
$var wire 4 Q a3_a0 [3:0] $end
$var reg 4 R OUTR [3:0] $end
$scope module inc $end
$var wire 1 N cin $end
$var wire 1 P cout $end
$var wire 4 S x3_x0 [3:0] $end
$var wire 1 T x3 $end
$var wire 1 U x2 $end
$var wire 1 V x1 $end
$var wire 1 W x0 $end
$var wire 4 X s3_s0 [3:0] $end
$upscope $end
$upscope $end
$upscope $end
$upscope $end
$enddefinitions $end
$comment Show the parameter values. $end
$dumpall
$end
#0
$dumpvars
bx X
xW
xV
xU
xT
bx S
bx R
bx Q
0P
bx O
0N
bx M
xL
xK
xJ
xI
bx H
bx G
bx F
0E
bx D
0C
bx B
xA
x@
x?
x>
bx =
bx <
bx ;
0:
bx 9
08
bx 7
x6
x5
x4
x3
bx 2
bx 1
bx 0
0/
bx .
b0 -
bx ,
bx +
bx *
bx )
0(
0'
0&
0%
bx $
bx #
bx "
bx !
$end
#1
b0 0
b0 7
b0 ;
b0 B
b0 F
b0 M
b0 Q
b0 X
03
04
05
06
0>
0?
0@
0A
0I
0J
0K
0L
0T
0U
0V
0W
b0 $
b0 ,
b0 .
b0 1
b0 2
b0 #
b0 +
b0 9
b0 <
b0 =
b0 "
b0 *
b0 D
b0 G
b0 H
b0 !
b0 )
b0 O
b0 R
b0 S
#5
1&
#10
b1 0
b1 7
0&
1'
1(
#15
1&
#17
b10 0
b10 7
16
b1 $
b1 ,
b1 .
b1 1
b1 2
#20
0&
#25
1&
#27
b11 0
b11 7
15
06
b10 $
b10 ,
b10 .
b10 1
b10 2
#30
0&
#35
1&
#37
b100 0
b100 7
16
b11 $
b11 ,
b11 .
b11 1
b11 2
#40
0&
#45
1&
#47
b101 0
b101 7
14
05
06
b100 $
b100 ,
b100 .
b100 1
b100 2
#50
0&
#55
1&
#57
b110 0
b110 7
16
b101 $
b101 ,
b101 .
b101 1
b101 2
#60
0&
#65
1&
#67
b111 0
b111 7
15
06
b110 $
b110 ,
b110 .
b110 1
b110 2
#70
0&
#75
1&
#77
b1000 0
b1000 7
16
b111 $
b111 ,
b111 .
b111 1
b111 2
#80
0&
#85
1&
#87
b1001 0
b1001 7
13
04
05
06
b1000 $
b1000 ,
b1000 .
b1000 1
b1000 2
#90
0&
#95
1&
#97
b1 ;
b1 B
18
b1 -
1/
b0 0
b0 7
16
b1001 $
b1001 ,
b1001 .
b1001 1
b1001 2
#100
0&
#105
1&
#107
08
b0 -
0/
b1 0
b1 7
b1 ;
b1 B
03
06
1A
b0 $
b0 ,
b0 .
b0 1
b0 2
b1 #
b1 +
b1 9
b1 <
b1 =
#110
0&
#115
1&
#117
b10 0
b10 7
16
b1 $
b1 ,
b1 .
b1 1
b1 2
#120
0&
#125
1&
#127
b11 0
b11 7
15
06
b10 $
b10 ,
b10 .
b10 1
b10 2
#130
0&
#135
1&
#137
b100 0
b100 7
16
b11 $
b11 ,
b11 .
b11 1
b11 2
#140
0&
#145
1&
#147
b101 0
b101 7
14
05
06
b100 $
b100 ,
b100 .
b100 1
b100 2
#150
0&
#155
1&
#157
b110 0
b110 7
16
b101 $
b101 ,
b101 .
b101 1
b101 2
#160
0&
#165
1&
#167
b111 0
b111 7
15
06
b110 $
b110 ,
b110 .
b110 1
b110 2
#170
0&
#175
1&
#177
b1000 0
b1000 7
16
b111 $
b111 ,
b111 .
b111 1
b111 2
#180
0&
#185
1&
#187
b1001 0
b1001 7
13
04
05
06
b1000 $
b1000 ,
b1000 .
b1000 1
b1000 2
#190
0&
#195
1&
#197
b10 ;
b10 B
18
b1 -
1/
b0 0
b0 7
16
b1001 $
b1001 ,
b1001 .
b1001 1
b1001 2
#200
0&
#205
1&
#207
08
b0 -
0/
b1 0
b1 7
b10 ;
b10 B
03
06
1@
0A
b0 $
b0 ,
b0 .
b0 1
b0 2
b10 #
b10 +
b10 9
b10 <
b10 =
#210
0&
#215
1&
#217
b10 0
b10 7
16
b1 $
b1 ,
b1 .
b1 1
b1 2
#220
0&
#225
1&
#227
b11 0
b11 7
15
06
b10 $
b10 ,
b10 .
b10 1
b10 2
#230
0&
#235
1&
#237
b100 0
b100 7
16
b11 $
b11 ,
b11 .
b11 1
b11 2
#240
0&
#245
1&
#247
b101 0
b101 7
14
05
06
b100 $
b100 ,
b100 .
b100 1
b100 2
#250
0&
#255
1&
#257
b110 0
b110 7
16
b101 $
b101 ,
b101 .
b101 1
b101 2
#260
0&
#265
1&
#267
b111 0
b111 7
15
06
b110 $
b110 ,
b110 .
b110 1
b110 2
#270
0&
#275
1&
#277
b1000 0
b1000 7
16
b111 $
b111 ,
b111 .
b111 1
b111 2
#280
0&
#285
1&
#287
b1001 0
b1001 7
13
04
05
06
b1000 $
b1000 ,
b1000 .
b1000 1
b1000 2
#290
0&
#295
1&
#297
b11 ;
b11 B
18
b1 -
1/
b0 0
b0 7
16
b1001 $
b1001 ,
b1001 .
b1001 1
b1001 2
#300
0&
#305
1&
#307
08
b0 -
0/
b1 0
b1 7
b11 ;
b11 B
03
06
1A
b0 $
b0 ,
b0 .
b0 1
b0 2
b11 #
b11 +
b11 9
b11 <
b11 =
#310
0&
#315
1&
#317
b10 0
b10 7
16
b1 $
b1 ,
b1 .
b1 1
b1 2
#320
0&
#325
1&
#327
b11 0
b11 7
15
06
b10 $
b10 ,
b10 .
b10 1
b10 2
#330
0&
#335
1&
#337
b100 0
b100 7
16
b11 $
b11 ,
b11 .
b11 1
b11 2
#340
0&
#345
1&
#347
b101 0
b101 7
14
05
06
b100 $
b100 ,
b100 .
b100 1
b100 2
#350
0&
#355
1&
#357
b110 0
b110 7
16
b101 $
b101 ,
b101 .
b101 1
b101 2
#360
0&
#365
1&
#367
b111 0
b111 7
15
06
b110 $
b110 ,
b110 .
b110 1
b110 2
#370
0&
#375
1&
#377
b1000 0
b1000 7
16
b111 $
b111 ,
b111 .
b111 1
b111 2
#380
0&
#385
1&
#387
b1001 0
b1001 7
13
04
05
06
b1000 $
b1000 ,
b1000 .
b1000 1
b1000 2
#390
0&
#395
1&
#397
b100 ;
b100 B
18
b1 -
1/
b0 0
b0 7
16
b1001 $
b1001 ,
b1001 .
b1001 1
b1001 2
#400
0&
#405
1&
#407
08
b0 -
0/
b1 0
b1 7
b100 ;
b100 B
03
06
1?
0@
0A
b0 $
b0 ,
b0 .
b0 1
b0 2
b100 #
b100 +
b100 9
b100 <
b100 =
#410
0&
#415
1&
#417
b10 0
b10 7
16
b1 $
b1 ,
b1 .
b1 1
b1 2
#420
0&
#425
1&
#427
b11 0
b11 7
15
06
b10 $
b10 ,
b10 .
b10 1
b10 2
#430
0&
#435
1&
#437
b100 0
b100 7
16
b11 $
b11 ,
b11 .
b11 1
b11 2
#440
0&
#445
1&
#447
b101 0
b101 7
14
05
06
b100 $
b100 ,
b100 .
b100 1
b100 2
#450
0&
#455
1&
#457
b110 0
b110 7
16
b101 $
b101 ,
b101 .
b101 1
b101 2
#460
0&
#465
1&
#467
b111 0
b111 7
15
06
b110 $
b110 ,
b110 .
b110 1
b110 2
#470
0&
#475
1&
#477
b1000 0
b1000 7
16
b111 $
b111 ,
b111 .
b111 1
b111 2
#480
0&
#485
1&
#487
b1001 0
b1001 7
13
04
05
06
b1000 $
b1000 ,
b1000 .
b1000 1
b1000 2
#490
0&
#495
1&
#497
b101 ;
b101 B
18
b1 -
1/
b0 0
b0 7
16
b1001 $
b1001 ,
b1001 .
b1001 1
b1001 2
#500
0&
#505
1&
#507
08
b0 -
0/
b1 0
b1 7
b101 ;
b101 B
03
06
1A
b0 $
b0 ,
b0 .
b0 1
b0 2
b101 #
b101 +
b101 9
b101 <
b101 =
#510
0&
#515
1&
#517
b10 0
b10 7
16
b1 $
b1 ,
b1 .
b1 1
b1 2
#520
0&
#525
1&
#527
b11 0
b11 7
15
06
b10 $
b10 ,
b10 .
b10 1
b10 2
#530
0&
#535
1&
#537
b100 0
b100 7
16
b11 $
b11 ,
b11 .
b11 1
b11 2
#540
0&
#545
1&
#547
b101 0
b101 7
14
05
06
b100 $
b100 ,
b100 .
b100 1
b100 2
#550
0&
#555
1&
#557
b110 0
b110 7
16
b101 $
b101 ,
b101 .
b101 1
b101 2
#560
0&
#565
1&
#567
b111 0
b111 7
15
06
b110 $
b110 ,
b110 .
b110 1
b110 2
#570
0&
#575
1&
#577
b1000 0
b1000 7
16
b111 $
b111 ,
b111 .
b111 1
b111 2
#580
0&
#585
1&
#587
b1001 0
b1001 7
13
04
05
06
b1000 $
b1000 ,
b1000 .
b1000 1
b1000 2
#590
0&
#595
1&
#597
b110 ;
b110 B
18
b1 -
1/
b0 0
b0 7
16
b1001 $
b1001 ,
b1001 .
b1001 1
b1001 2
#600
0&
#605
1&
#607
08
b0 -
0/
b1 0
b1 7
b110 ;
b110 B
03
06
1@
0A
b0 $
b0 ,
b0 .
b0 1
b0 2
b110 #
b110 +
b110 9
b110 <
b110 =
#610
0&
#615
1&
#617
b10 0
b10 7
16
b1 $
b1 ,
b1 .
b1 1
b1 2
#620
0&
#625
1&
#627
b11 0
b11 7
15
06
b10 $
b10 ,
b10 .
b10 1
b10 2
#630
0&
#635
1&
#637
b100 0
b100 7
16
b11 $
b11 ,
b11 .
b11 1
b11 2
#640
0&
#645
1&
#647
b101 0
b101 7
14
05
06
b100 $
b100 ,
b100 .
b100 1
b100 2
#650
0&
#655
1&
#657
b110 0
b110 7
16
b101 $
b101 ,
b101 .
b101 1
b101 2
#660
0&
#665
1&
#667
b111 0
b111 7
15
06
b110 $
b110 ,
b110 .
b110 1
b110 2
#670
0&
#675
1&
#677
b1000 0
b1000 7
16
b111 $
b111 ,
b111 .
b111 1
b111 2
#680
0&
#685
1&
#687
b1001 0
b1001 7
13
04
05
06
b1000 $
b1000 ,
b1000 .
b1000 1
b1000 2
#690
0&
#695
1&
#697
b111 ;
b111 B
18
b1 -
1/
b0 0
b0 7
16
b1001 $
b1001 ,
b1001 .
b1001 1
b1001 2
#700
0&
#705
1&
#707
08
b0 -
0/
b1 0
b1 7
b111 ;
b111 B
03
06
1A
b0 $
b0 ,
b0 .
b0 1
b0 2
b111 #
b111 +
b111 9
b111 <
b111 =
#710
0&
#715
1&
#717
b10 0
b10 7
16
b1 $
b1 ,
b1 .
b1 1
b1 2
#720
0&
#725
1&
#727
b11 0
b11 7
15
06
b10 $
b10 ,
b10 .
b10 1
b10 2
#730
0&
#735
1&
#737
b100 0
b100 7
16
b11 $
b11 ,
b11 .
b11 1
b11 2
#740
0&
#745
1&
#747
b101 0
b101 7
14
05
06
b100 $
b100 ,
b100 .
b100 1
b100 2
#750
0&
#755
1&
#757
b110 0
b110 7
16
b101 $
b101 ,
b101 .
b101 1
b101 2
#760
0&
#765
1&
#767
b111 0
b111 7
15
06
b110 $
b110 ,
b110 .
b110 1
b110 2
#770
0&
#775
1&
#777
b1000 0
b1000 7
16
b111 $
b111 ,
b111 .
b111 1
b111 2
#780
0&
#785
1&
#787
b1001 0
b1001 7
13
04
05
06
b1000 $
b1000 ,
b1000 .
b1000 1
b1000 2
#790
0&
#795
1&
#797
b1000 ;
b1000 B
18
b1 -
1/
b0 0
b0 7
16
b1001 $
b1001 ,
b1001 .
b1001 1
b1001 2
#800
0&
#805
1&
#807
08
b0 -
0/
b1 0
b1 7
b1000 ;
b1000 B
03
06
1>
0?
0@
0A
b0 $
b0 ,
b0 .
b0 1
b0 2
b1000 #
b1000 +
b1000 9
b1000 <
b1000 =
#810
0&
#815
1&
#817
b10 0
b10 7
16
b1 $
b1 ,
b1 .
b1 1
b1 2
#820
0&
#825
1&
#827
b11 0
b11 7
15
06
b10 $
b10 ,
b10 .
b10 1
b10 2
#830
0&
#835
1&
#837
b100 0
b100 7
16
b11 $
b11 ,
b11 .
b11 1
b11 2
#840
0&
#845
1&
#847
b101 0
b101 7
14
05
06
b100 $
b100 ,
b100 .
b100 1
b100 2
#850
0&
#855
1&
#857
b110 0
b110 7
16
b101 $
b101 ,
b101 .
b101 1
b101 2
#860
0&
#865
1&
#867
b111 0
b111 7
15
06
b110 $
b110 ,
b110 .
b110 1
b110 2
#870
0&
#875
1&
#877
b1000 0
b1000 7
16
b111 $
b111 ,
b111 .
b111 1
b111 2
#880
0&
#885
1&
#887
b1001 0
b1001 7
13
04
05
06
b1000 $
b1000 ,
b1000 .
b1000 1
b1000 2
#890
0&
#895
1&
#897
b1001 ;
b1001 B
18
b1 -
1/
b0 0
b0 7
16
b1001 $
b1001 ,
b1001 .
b1001 1
b1001 2
#900
0&
#905
1&
#907
b0 F
b0 M
08
0C
0/
b0 -
0:
b1 0
b1 7
b1001 ;
b1001 B
03
06
1A
b0 $
b0 ,
b0 .
b0 1
b0 2
b1001 #
b1001 +
b1001 9
b1001 <
b1001 =
#910
0&
#915
1&
#917
b10 0
b10 7
16
b1 $
b1 ,
b1 .
b1 1
b1 2
#920
0&
#925
1&
#927
b11 0
b11 7
15
06
b10 $
b10 ,
b10 .
b10 1
b10 2
#930
0&
#935
1&
#937
b100 0
b100 7
16
b11 $
b11 ,
b11 .
b11 1
b11 2
#940
0&
#945
1&
#947
b101 0
b101 7
14
05
06
b100 $
b100 ,
b100 .
b100 1
b100 2
#950
0&
#955
1&
#957
b110 0
b110 7
16
b101 $
b101 ,
b101 .
b101 1
b101 2
#960
0&
#965
1&
#967
b111 0
b111 7
15
06
b110 $
b110 ,
b110 .
b110 1
b110 2
#970
0&
#975
1&
#977
b1000 0
b1000 7
16
b111 $
b111 ,
b111 .
b111 1
b111 2
#980
0&
#985
1&
#987
b1001 0
b1001 7
13
04
05
06
b1000 $
b1000 ,
b1000 .
b1000 1
b1000 2
#990
0&
#995
1&
#997
b1 F
b1 M
1C
b0 ;
b0 B
1:
18
b11 -
1/
b0 0
b0 7
16
b1001 $
b1001 ,
b1001 .
b1001 1
b1001 2
#1000
0&
#1005
1&
#1007
08
0C
0/
b0 -
0:
b1 0
b1 7
b0 ;
b0 B
b1 F
b1 M
03
06
0>
0A
1L
b0 $
b0 ,
b0 .
b0 1
b0 2
b0 #
b0 +
b0 9
b0 <
b0 =
b1 "
b1 *
b1 D
b1 G
b1 H
#1010
0&
#1015
1&
#1017
b10 0
b10 7
16
b1 $
b1 ,
b1 .
b1 1
b1 2
#1020
0&
#1025
1&
#1027
b11 0
b11 7
15
06
b10 $
b10 ,
b10 .
b10 1
b10 2
#1030
0&
#1035
1&
#1037
b100 0
b100 7
16
b11 $
b11 ,
b11 .
b11 1
b11 2
#1040
0&
#1045
1&
#1047
b101 0
b101 7
14
05
06
b100 $
b100 ,
b100 .
b100 1
b100 2
#1050
0&
#1055
1&
#1057
b110 0
b110 7
16
b101 $
b101 ,
b101 .
b101 1
b101 2
#1060
0&
#1065
1&
#1067
b111 0
b111 7
15
06
b110 $
b110 ,
b110 .
b110 1
b110 2
#1070
0&
#1075
1&
#1077
b1000 0
b1000 7
16
b111 $
b111 ,
b111 .
b111 1
b111 2
#1080
0&
#1085
1&
#1087
b1001 0
b1001 7
13
04
05
06
b1000 $
b1000 ,
b1000 .
b1000 1
b1000 2
#1090
0&
#1095
1&
#1097
b1 ;
b1 B
18
b1 -
1/
b0 0
b0 7
16
b1001 $
b1001 ,
b1001 .
b1001 1
b1001 2
#1100
0&
#1105
1&
#1107
08
b0 -
0/
b1 0
b1 7
b1 ;
b1 B
03
06
1A
b0 $
b0 ,
b0 .
b0 1
b0 2
b1 #
b1 +
b1 9
b1 <
b1 =
#1110
0&
#1115
1&
#1117
b10 0
b10 7
16
b1 $
b1 ,
b1 .
b1 1
b1 2
#1120
0&
#1125
1&
#1127
b11 0
b11 7
15
06
b10 $
b10 ,
b10 .
b10 1
b10 2
#1130
0&
#1135
1&
#1137
b100 0
b100 7
16
b11 $
b11 ,
b11 .
b11 1
b11 2
#1140
0&
#1145
1&
#1147
b101 0
b101 7
14
05
06
b100 $
b100 ,
b100 .
b100 1
b100 2
#1150
0&
#1155
1&
#1157
b110 0
b110 7
16
b101 $
b101 ,
b101 .
b101 1
b101 2
#1160
0&
#1165
1&
#1167
b111 0
b111 7
15
06
b110 $
b110 ,
b110 .
b110 1
b110 2
#1170
0&
#1175
1&
#1177
b1000 0
b1000 7
16
b111 $
b111 ,
b111 .
b111 1
b111 2
#1180
0&
#1185
1&
#1187
b1001 0
b1001 7
13
04
05
06
b1000 $
b1000 ,
b1000 .
b1000 1
b1000 2
#1190
0&
#1195
1&
#1197
b10 ;
b10 B
18
b1 -
1/
b0 0
b0 7
16
b1001 $
b1001 ,
b1001 .
b1001 1
b1001 2
#1200
0&
#1205
1&
#1207
08
b0 -
0/
b1 0
b1 7
b10 ;
b10 B
03
06
1@
0A
b0 $
b0 ,
b0 .
b0 1
b0 2
b10 #
b10 +
b10 9
b10 <
b10 =
#1210
0&
#1215
1&
#1217
b10 0
b10 7
16
b1 $
b1 ,
b1 .
b1 1
b1 2
#1220
0&
#1225
1&
#1227
b11 0
b11 7
15
06
b10 $
b10 ,
b10 .
b10 1
b10 2
#1230
0&
#1235
1&
#1237
b100 0
b100 7
16
b11 $
b11 ,
b11 .
b11 1
b11 2
#1240
0&
#1245
1&
#1247
b101 0
b101 7
14
05
06
b100 $
b100 ,
b100 .
b100 1
b100 2
#1250
0&
#1255
1&
#1257
b110 0
b110 7
16
b101 $
b101 ,
b101 .
b101 1
b101 2
#1260
0&
#1265
1&
#1267
b111 0
b111 7
15
06
b110 $
b110 ,
b110 .
b110 1
b110 2
#1270
0&
#1275
1&
#1277
b1000 0
b1000 7
16
b111 $
b111 ,
b111 .
b111 1
b111 2
#1280
0&
#1285
1&
#1287
b1001 0
b1001 7
13
04
05
06
b1000 $
b1000 ,
b1000 .
b1000 1
b1000 2
#1290
0&
#1295
1&
#1297
b11 ;
b11 B
18
b1 -
1/
b0 0
b0 7
16
b1001 $
b1001 ,
b1001 .
b1001 1
b1001 2
#1300
0&
#1305
1&
#1307
08
b0 -
0/
b1 0
b1 7
b11 ;
b11 B
03
06
1A
b0 $
b0 ,
b0 .
b0 1
b0 2
b11 #
b11 +
b11 9
b11 <
b11 =
#1310
0&
#1315
1&
#1317
b10 0
b10 7
16
b1 $
b1 ,
b1 .
b1 1
b1 2
#1320
0&
#1325
1&
#1327
b11 0
b11 7
15
06
b10 $
b10 ,
b10 .
b10 1
b10 2
#1330
0&
#1335
1&
#1337
b100 0
b100 7
16
b11 $
b11 ,
b11 .
b11 1
b11 2
#1340
0&
#1345
1&
#1347
b101 0
b101 7
14
05
06
b100 $
b100 ,
b100 .
b100 1
b100 2
#1350
0&
#1355
1&
#1357
b110 0
b110 7
16
b101 $
b101 ,
b101 .
b101 1
b101 2
#1360
0&
#1365
1&
#1367
b111 0
b111 7
15
06
b110 $
b110 ,
b110 .
b110 1
b110 2
#1370
0&
#1375
1&
#1377
b1000 0
b1000 7
16
b111 $
b111 ,
b111 .
b111 1
b111 2
#1380
0&
#1385
1&
#1387
b1001 0
b1001 7
13
04
05
06
b1000 $
b1000 ,
b1000 .
b1000 1
b1000 2
#1390
0&
#1395
1&
#1397
b100 ;
b100 B
18
b1 -
1/
b0 0
b0 7
16
b1001 $
b1001 ,
b1001 .
b1001 1
b1001 2
#1400
0&
#1405
1&
#1407
08
b0 -
0/
b1 0
b1 7
b100 ;
b100 B
03
06
1?
0@
0A
b0 $
b0 ,
b0 .
b0 1
b0 2
b100 #
b100 +
b100 9
b100 <
b100 =
#1410
0&
#1415
1&
#1417
b10 0
b10 7
16
b1 $
b1 ,
b1 .
b1 1
b1 2
#1420
0&
#1425
1&
#1427
b11 0
b11 7
15
06
b10 $
b10 ,
b10 .
b10 1
b10 2
#1430
0&
#1435
1&
#1437
b100 0
b100 7
16
b11 $
b11 ,
b11 .
b11 1
b11 2
#1440
0&
#1445
1&
#1447
b101 0
b101 7
14
05
06
b100 $
b100 ,
b100 .
b100 1
b100 2
#1450
0&
#1455
1&
#1457
b110 0
b110 7
16
b101 $
b101 ,
b101 .
b101 1
b101 2
#1460
0&
#1465
1&
#1467
b111 0
b111 7
15
06
b110 $
b110 ,
b110 .
b110 1
b110 2
#1470
0&
#1475
1&
#1477
b1000 0
b1000 7
16
b111 $
b111 ,
b111 .
b111 1
b111 2
#1480
0&
#1485
1&
#1487
b1001 0
b1001 7
13
04
05
06
b1000 $
b1000 ,
b1000 .
b1000 1
b1000 2
#1490
0&
#1495
1&
#1497
b101 ;
b101 B
18
b1 -
1/
b0 0
b0 7
16
b1001 $
b1001 ,
b1001 .
b1001 1
b1001 2
#1500
0&
#1505
1&
#1507
08
b0 -
0/
b1 0
b1 7
b101 ;
b101 B
03
06
1A
b0 $
b0 ,
b0 .
b0 1
b0 2
b101 #
b101 +
b101 9
b101 <
b101 =
#1510
0&
#1515
1&
#1517
b10 0
b10 7
16
b1 $
b1 ,
b1 .
b1 1
b1 2
#1520
0&
#1525
1&
#1527
b11 0
b11 7
15
06
b10 $
b10 ,
b10 .
b10 1
b10 2
#1530
0&
#1535
1&
#1537
b100 0
b100 7
16
b11 $
b11 ,
b11 .
b11 1
b11 2
#1540
0&
#1545
1&
#1547
b101 0
b101 7
14
05
06
b100 $
b100 ,
b100 .
b100 1
b100 2
#1550
0&
#1555
1&
#1557
b110 0
b110 7
16
b101 $
b101 ,
b101 .
b101 1
b101 2
#1560
0&
#1565
1&
#1567
b111 0
b111 7
15
06
b110 $
b110 ,
b110 .
b110 1
b110 2
#1570
0&
#1575
1&
#1577
b1000 0
b1000 7
16
b111 $
b111 ,
b111 .
b111 1
b111 2
#1580
0&
#1585
1&
#1587
b1001 0
b1001 7
13
04
05
06
b1000 $
b1000 ,
b1000 .
b1000 1
b1000 2
#1590
0&
#1595
1&
#1597
b110 ;
b110 B
18
b1 -
1/
b0 0
b0 7
16
b1001 $
b1001 ,
b1001 .
b1001 1
b1001 2
#1600
0&
#1605
1&
