verilog/10-22/b2_halfadder.v
// un half adder in base 2 che calcola @x + @cin, mettendo il 
// risultato in @s e il riporto in @cout
// module b2_halfadder(x, cin, s, cout);
// 	input x, cin;
// 	output s, cout;
// 
// 	assign {s, cout} = ({x, cin} == 'B00) ? 'B00:
// 										 ({x, cin} == 'B01) ? 'B10:
// 										 ({x, cin} == 'B10) ? 'B10:
// 									 /*({x, cin} == 'B11)?*/'B01;
// endmodule

// implementazione a porte logiche
module b2_halfadder(x, cin, s, cout);
	input x, cin;
	output s, cout;

	assign s = x ^ cin;
	assign cout = x & cin;
endmodule

verilog/11-07/up_counters/b2_up_counter.v
// un contatore up a una cifra in base 2 che prende @ei come enabler
// e mette la sua uscita in @q, con eventuale riporto in @eu 
module b2_up_counter(eu, q, ei, clock, reset_);
  input clock, reset_;
  input ei;
  output eu, q;
  
	reg OUTR;
  assign q = OUTR;	
  
	wire a; // l'uscita dell'incrementatore
	b2_halfadder inc (
		.x(q), .cin(ei),
		.s(a), .cout(eu)
	);

  always @(reset_ == 0) #1 OUTR <= 0;
  always @(posedge clock) if (reset_==1) #2 OUTR <= a;
endmodule

verilog/11-07/tests/b2_up_counter_bench.v
module testbench();
	reg t_clock, t_reset_;
	reg t_ei;
	wire t_eu;
	wire t_q;

	b2_up_counter count (
		.clock(t_clock), .reset_(t_reset_),
		.ei(t_ei),
		.eu(t_eu), .q(t_q)
	);
	
	initial begin
    forever #5 t_clock = ~t_clock; 
	end

	initial begin
		$dumpfile("b2_up_counter_bench_waveform.vcd");
		$dumpvars;	

		t_clock = 0;
		t_reset_ = 0;
		t_ei = 0;

		#10 

		t_reset_ = 1;
		t_ei = 1;

		#200;

		$finish;
	end
endmodule

verilog/11-07/tests/b2_up_counter_bench_waveform.vcd
$date
	Wed Nov 20 11:02:48 2024
$end
$version
	Icarus Verilog
$end
$timescale
	1s
$end
$scope module testbench $end
$var wire 1 ! t_q $end
$var wire 1 " t_eu $end
$var reg 1 # t_clock $end
$var reg 1 $ t_ei $end
$var reg 1 % t_reset_ $end
$scope module count $end
$var wire 1 # clock $end
$var wire 1 $ ei $end
$var wire 1 ! q $end
$var wire 1 % reset_ $end
$var wire 1 " eu $end
$var wire 1 & a $end
$var reg 1 ! OUTR $end
$scope module inc $end
$var wire 1 $ cin $end
$var wire 1 " cout $end
$var wire 1 & s $end
$var wire 1 ! x $end
$upscope $end
$upscope $end
$upscope $end
$enddefinitions $end
$comment Show the parameter values. $end
$dumpall
$end
#0
$dumpvars
x&
0%
0$
0#
0"
x!
$end
#1
0&
0!
#5
1#
#10
1&
0#
1$
1%
#15
1#
#17
0&
1"
1!
#20
0#
#25
1#
#27
1&
0"
0!
#30
0#
#35
1#
#37
0&
1"
1!
#40
0#
#45
1#
#47
1&
0"
0!
#50
0#
#55
1#
#57
0&
1"
1!
#60
0#
#65
1#
#67
1&
0"
0!
#70
0#
#75
1#
#77
0&
1"
1!
#80
0#
#85
1#
#87
1&
0"
0!
#90
0#
#95
1#
#97
0&
1"
1!
#100
0#
#105
1#
#107
1&
0"
0!
#110
0#
#115
1#
#117
0&
1"
1!
#120
0#
#125
1#
#127
1&
0"
0!
#130
0#
#135
1#
#137
0&
1"
1!
#140
0#
#145
1#
#147
1&
0"
0!
#150
0#
#155
1#
#157
0&
1"
1!
#160
0#
#165
1#
#167
1&
0"
0!
#170
0#
#175
1#
#177
0&
1"
1!
#180
0#
#185
1#
#187
1&
0"
0!
#190
0#
#195
1#
#197
0&
1"
1!
#200
0#
#205
1#
#207
1&
0"
0!
