verilog/10-22/b3_halfadder.v
// un half adder in base 3 che calcola @x1_x0 + @cin, mettendo il 
// risultato in @s1_s0 e il riporto in @cout
// module b3_halfadder(x1_x0, cin, s1_s0, cout);
// 	input[1:0] x1_x0;
// 	input cin;
// 	output[1:0] s1_s0;
// 	output cout;
// 
// 	assign {s1_s0, cout} = ({x1_x0, cin} == 'B000) ? 'B000:
// 										 		 ({x1_x0, cin} == 'B001) ? 'B010:
// 										 		 ({x1_x0, cin} == 'B010) ? 'B010:
// 										 		 ({x1_x0, cin} == 'B011) ? 'B100:
// 										 		 ({x1_x0, cin} == 'B100) ? 'B100:
// 										 		 ({x1_x0, cin} == 'B101) ? 'B001:
// 										 		 /* 		 don't care 		*/ 'BXXX;
// endmodule

// implementazione a porte logiche
module b3_halfadder(x1_x0, cin, s1_s0, cout);
	input[1:0] x1_x0;
	wire x1 = x1_x0[1];
	wire x0 = x1_x0[0];

	input cin;
	
	output[1:0] s1_s0;	
	output cout;

	assign s1_s0[1] = (x1 & ~cin) | (x0 & cin);
	assign s1_s0[0] = (x0 & ~cin) | ~x1 & ~x0 & cin;
	assign cout = x1 & cin;
endmodule

verilog/11-07/b3_up_counter.v
// un contatore up a una cifra in base 3 che prende @ei come enabler
// e mette la sua uscita in @q1_q0, con eventuale riporto in @eu 
module b3_up_counter(eu, q1_q0, ei, clock, reset_);
  input clock, reset_;
  input ei;
  output eu;
	output[1:0] q1_q0;
  
	reg[1:0] OUTR;
  assign q1_q0 = OUTR;	
  
	wire[1:0] a1_a0; // l'uscita dell'incrementatore
	b3_halfadder inc (
		.x1_x0(q1_q0), .cin(ei),
		.s1_s0(a1_a0), .cout(eu)
	);

  always @(reset_ == 0) #1 OUTR <= 0;
  always @(posedge clock) if (reset_==1) #2 OUTR <= a1_a0;
endmodule

verilog/11-07/tests/b3_up_counter_bench.v
module testbench();
	reg t_clock, t_reset_;
	reg t_ei;
	wire t_eu;
	wire[1:0] t_q1_q0;

	b3_up_counter count (
		.clock(t_clock), .reset_(t_reset_),
		.ei(t_ei),
		.eu(t_eu), .q1_q0(t_q1_q0)
	);
	
	initial begin
    forever #5 t_clock = ~t_clock; 
	end

	initial begin
		$dumpfile("b3_up_counter_bench_waveform.vcd");
		$dumpvars;	

		t_clock = 0;
		t_reset_ = 0;
		t_ei = 0;

		#10 

		t_reset_ = 1;
		t_ei = 1;

		#200;

		$finish;
	end
endmodule

verilog/11-07/tests/b3_up_counter_bench_waveform.vcd
$date
	Wed Nov 20 11:03:08 2024
$end
$version
	Icarus Verilog
$end
$timescale
	1s
$end
$scope module testbench $end
$var wire 2 ! t_q1_q0 [1:0] $end
$var wire 1 " t_eu $end
$var reg 1 # t_clock $end
$var reg 1 $ t_ei $end
$var reg 1 % t_reset_ $end
$scope module count $end
$var wire 1 # clock $end
$var wire 1 $ ei $end
$var wire 2 & q1_q0 [1:0] $end
$var wire 1 % reset_ $end
$var wire 1 " eu $end
$var wire 2 ' a1_a0 [1:0] $end
$var reg 2 ( OUTR [1:0] $end
$scope module inc $end
$var wire 1 $ cin $end
$var wire 1 " cout $end
$var wire 2 ) x1_x0 [1:0] $end
$var wire 1 * x1 $end
$var wire 1 + x0 $end
$var wire 2 , s1_s0 [1:0] $end
$upscope $end
$upscope $end
$upscope $end
$enddefinitions $end
$comment Show the parameter values. $end
$dumpall
$end
#0
$dumpvars
bx ,
x+
x*
bx )
bx (
bx '
bx &
0%
0$
0#
0"
bx !
$end
#1
b0 '
b0 ,
0*
0+
b0 !
b0 &
b0 (
b0 )
#5
1#
#10
b1 '
b1 ,
0#
1$
1%
#15
1#
#17
b10 '
b10 ,
1+
b1 !
b1 &
b1 (
b1 )
#20
0#
#25
1#
#27
b0 '
b0 ,
1"
1*
0+
b10 !
b10 &
b10 (
b10 )
#30
0#
#35
1#
#37
b1 '
b1 ,
0"
0*
b0 !
b0 &
b0 (
b0 )
#40
0#
#45
1#
#47
b10 '
b10 ,
1+
b1 !
b1 &
b1 (
b1 )
#50
0#
#55
1#
#57
b0 '
b0 ,
1"
1*
0+
b10 !
b10 &
b10 (
b10 )
#60
0#
#65
1#
#67
b1 '
b1 ,
0"
0*
b0 !
b0 &
b0 (
b0 )
#70
0#
#75
1#
#77
b10 '
b10 ,
1+
b1 !
b1 &
b1 (
b1 )
#80
0#
#85
1#
#87
b0 '
b0 ,
1"
1*
0+
b10 !
b10 &
b10 (
b10 )
#90
0#
#95
1#
#97
b1 '
b1 ,
0"
0*
b0 !
b0 &
b0 (
b0 )
#100
0#
#105
1#
#107
b10 '
b10 ,
1+
b1 !
b1 &
b1 (
b1 )
#110
0#
#115
1#
#117
b0 '
b0 ,
1"
1*
0+
b10 !
b10 &
b10 (
b10 )
#120
0#
#125
1#
#127
b1 '
b1 ,
0"
0*
b0 !
b0 &
b0 (
b0 )
#130
0#
#135
1#
#137
b10 '
b10 ,
1+
b1 !
b1 &
b1 (
b1 )
#140
0#
#145
1#
#147
b0 '
b0 ,
1"
1*
0+
b10 !
b10 &
b10 (
b10 )
#150
0#
#155
1#
#157
b1 '
b1 ,
0"
0*
b0 !
b0 &
b0 (
b0 )
#160
0#
#165
1#
#167
b10 '
b10 ,
1+
b1 !
b1 &
b1 (
b1 )
#170
0#
#175
1#
#177
b0 '
b0 ,
1"
1*
0+
b10 !
b10 &
b10 (
b10 )
#180
0#
#185
1#
#187
b1 '
b1 ,
0"
0*
b0 !
b0 &
b0 (
b0 )
#190
0#
#195
1#
#197
b10 '
b10 ,
1+
b1 !
b1 &
b1 (
b1 )
#200
0#
#205
1#
#207
b0 '
b0 ,
1"
1*
0+
b10 !
b10 &
b10 (
b10 )
